Traffic_light_verilog/TrafficLight/Light_counter.v
// Light Counter module in Verilog
`timescale 1ns/1ps

module Light_Counter #(
  parameter pGREEN_INIT_VAL = 14,
  parameter pYELLOW_INIT_VAL = 2,
  parameter pRED_INIT_VAL = 17,
  parameter pCNT_WIDTH = 5, // $clog2(pRED_INIT_VAL+1) = 5 for pRED_INIT_VAL=17
  parameter pINIT_WIDTH = 3
)
(
  input wire clk,
  input wire en,
  input wire rst_n,
  input wire [pINIT_WIDTH-1:0] init,
  output wire last,
  output reg [pCNT_WIDTH-1:0] cnt_out
);
  
  // Light indices
  parameter pGREEN_IDX = 0;
  parameter pYELLOW_IDX = 1;
  parameter pRED_IDX = 2;
  
  // Initialize counter to handle X at simulation start
  initial begin
    cnt_out = pYELLOW_INIT_VAL;
  end
  
  // Counter process
  always @(posedge clk or negedge rst_n) begin
    if(!rst_n) begin
      cnt_out <= pYELLOW_INIT_VAL;
    end
    else if(init[pGREEN_IDX]) begin
      cnt_out <= pGREEN_INIT_VAL;
    end
    else if(init[pYELLOW_IDX]) begin
      cnt_out <= pYELLOW_INIT_VAL;
    end
    else if(init[pRED_IDX]) begin
      cnt_out <= pRED_INIT_VAL;
    end 
    else if(en) begin
      if(cnt_out != 0) begin
        cnt_out <= cnt_out - 1;
      end
    end
  end
  
  // Output logic
  assign last = (cnt_out == 0) ? 1'b1 : 1'b0;
  
endmodule

Traffic_light_verilog/LightCounter/Light_counter_tb.v
// Light Counter Testbench in Verilog
`timescale 1ns/1ps

module Light_Counter_tb;

  // Parameters
  parameter pGREEN_INIT_VAL = 14;
  parameter pYELLOW_INIT_VAL = 2;
  parameter pRED_INIT_VAL = 17;
  parameter pCNT_WIDTH = 5; // $clog2(pRED_INIT_VAL+1) = 5 for pRED_INIT_VAL=17
  parameter pINIT_WIDTH = 3;

  // Signals
  reg clk;
  reg en;
  reg rst_n;
  reg [pINIT_WIDTH-1:0] init;
  wire last;
  wire [pCNT_WIDTH-1:0] cnt_out;

  // Instantiate the DUT
  Light_Counter #(
    .pGREEN_INIT_VAL(pGREEN_INIT_VAL),
    .pYELLOW_INIT_VAL(pYELLOW_INIT_VAL),
    .pRED_INIT_VAL(pRED_INIT_VAL),
    .pCNT_WIDTH(pCNT_WIDTH),
    .pINIT_WIDTH(pINIT_WIDTH)
  ) dut (
    .clk(clk),
    .en(en),
    .rst_n(rst_n),
    .init(init),
    .last(last),
    .cnt_out(cnt_out)
  );
  
  // Clock generation
  always #2 clk = ~clk;
  
  // Initialize simulation
  initial begin
    $dumpfile("dump.vcd");
    $dumpvars(0, Light_Counter_tb);
    Start_Simulation;
    RESET;
    TEST_CASE;
  end
  
  // Tasks
  task Start_Simulation; begin
    $display("----------------------------------------------");  
    $display("------------------   -----------------------");  
    $display("----------- SIMULATION RESULT ----------------");  
    $display("--------------       -------------------");  
    $display("----------------     ---------------------");  
    $display("----------------------------------------------");  
  end
  endtask
  
  task RESET; begin
    rst_n = 0;
    en = 0;
    clk = 0;
    init = 0;
    #2
    rst_n = 1;
  end
  endtask
  
  task TEST_CASE; begin
    $monitor("TIME=%d , clk=%b , rst_n= %b , en=%b , init=%3b , last=%b , cnt out=%d",
             $time, clk, rst_n, en, init, last, cnt_out);

    #2 en = 1;
    #2 init = 3'b100; // RED
    #5 init = 3'b000;
    #70 init = 3'b010; // YELLOW
    #5 init = 3'b000;
    #10 init = 3'b001; // GREEN
    #5 init = 3'b000;
    #60;
    endsimulation;
  end
  endtask
  
  task endsimulation; begin  
    $display("-------------- THE SIMULATION FINISHED ------------");  
    $finish;  
  end  
  endtask
  
  task display_State_Simulation; begin
    if(init == 3'b100) begin
      $display("==========RED LIGHT==========");
    end
    else if(init == 3'b010) begin
      $display("==========YELLOW LIGHT==========");
    end
    else if(init == 3'b001) begin
      $display("==========GREEN LIGHT==========");
    end
    else begin
      $display("==========Count==========");
    end
  end
  endtask
  
  // Display state on each positive clock edge
  always @(posedge clk) begin
    display_State_Simulation;
  end
  
endmodule

Traffic_light_verilog/LightCounter/dump.vcd
$date
	Tue Jun 10 01:52:45 2025
$end
$version
	Icarus Verilog
$end
$timescale
	1ps
$end
$scope module Light_Counter_tb $end
$var wire 1 ! last $end
$var wire 5 " cnt_out [4:0] $end
$var parameter 32 # pCNT_WIDTH $end
$var parameter 32 $ pGREEN_INIT_VAL $end
$var parameter 32 % pINIT_WIDTH $end
$var parameter 32 & pRED_INIT_VAL $end
$var parameter 32 ' pYELLOW_INIT_VAL $end
$var reg 1 ( clk $end
$var reg 1 ) en $end
$var reg 3 * init [2:0] $end
$var reg 1 + rst_n $end
$scope module dut $end
$var wire 1 ( clk $end
$var wire 1 ) en $end
$var wire 3 , init [2:0] $end
$var wire 1 + rst_n $end
$var wire 1 ! last $end
$var parameter 32 - pCNT_WIDTH $end
$var parameter 32 . pGREEN_IDX $end
$var parameter 32 / pGREEN_INIT_VAL $end
$var parameter 32 0 pINIT_WIDTH $end
$var parameter 32 1 pRED_IDX $end
$var parameter 32 2 pRED_INIT_VAL $end
$var parameter 32 3 pYELLOW_IDX $end
$var parameter 32 4 pYELLOW_INIT_VAL $end
$var reg 5 5 cnt_out [4:0] $end
$upscope $end
$scope task RESET $end
$upscope $end
$scope task Start_Simulation $end
$upscope $end
$scope task TEST_CASE $end
$upscope $end
$scope task display_State_Simulation $end
$upscope $end
$scope task endsimulation $end
$upscope $end
$upscope $end
$enddefinitions $end
$comment Show the parameter values. $end
$dumpall
b10 4
b1 3
b10001 2
b10 1
b11 0
b1110 /
b0 .
b101 -
b10 '
b10001 &
b11 %
b1110 $
b101 #
$end
#0
$dumpvars
b10 5
b0 ,
0+
b0 *
0)
0(
b10 "
0!
$end
#2000
1+
1(
#4000
1)
0(
#6000
b10001 "
b10001 5
b100 *
b100 ,
1(
#8000
0(
#10000
1(
#11000
b0 *
b0 ,
#12000
0(
#14000
b10000 "
b10000 5
1(
#16000
0(
#18000
b1111 "
b1111 5
1(
#20000
0(
#22000
b1110 "
b1110 5
1(
#24000
0(
#26000
b1101 "
b1101 5
1(
#28000
0(
#30000
b1100 "
b1100 5
1(
#32000
0(
#34000
b1011 "
b1011 5
1(
#36000
0(
#38000
b1010 "
b1010 5
1(
#40000
0(
#42000
b1001 "
b1001 5
1(
#44000
0(
#46000
b1000 "
b1000 5
1(
#48000
0(
#50000
b111 "
b111 5
1(
#52000
0(
#54000
b110 "
b110 5
1(
#56000
0(
#58000
b101 "
b101 5
1(
#60000
0(
#62000
b100 "
b100 5
1(
#64000
0(
#66000
b11 "
b11 5
1(
#68000
0(
#70000
b10 "
b10 5
1(
#72000
0(
#74000
b1 "
b1 5
1(
#76000
0(
#78000
1!
b0 "
b0 5
1(
#80000
0(
#81000
b10 *
b10 ,
#82000
0!
b10 "
b10 5
1(
#84000
0(
#86000
b1 "
b1 5
1(
b0 *
b0 ,
#88000
0(
#90000
1!
b0 "
b0 5
1(
#92000
0(
#94000
1(
#96000
0(
b1 *
b1 ,
#98000
0!
b1110 "
b1110 5
1(
#100000
0(
#101000
b0 *
b0 ,
#102000
b1101 "
b1101 5
1(
#104000
0(
#106000
b1100 "
b1100 5
1(
#108000
0(
#110000
b1011 "
b1011 5
1(
#112000
0(
#114000
b1010 "
b1010 5
1(
#116000
0(
#118000
b1001 "
b1001 5
1(
#120000
0(
#122000
b1000 "
b1000 5
1(
#124000
0(
#126000
b111 "
b111 5
1(
#128000
0(
#130000
b110 "
b110 5
1(
#132000
0(
#134000
b101 "
b101 5
1(
#136000
0(
#138000
b100 "
b100 5
1(
#140000
0(
#142000
b11 "
b11 5
1(
#144000
0(
#146000
b10 "
b10 5
1(
#148000
0(
#150000
b1 "
b1 5
1(
#152000
0(
#154000
1!
b0 "
b0 5
1(
