TrafficLight/Second_counter.v
// Second Counter module in Verilog - Fixed version
`timescale 1ns/1ps

module Second_counter #(
    parameter pSECOND_CNT_VALUE=99,
    parameter pMAX_VAL=pSECOND_CNT_VALUE
)
(
    input wire clk,  
    input wire en,
    input wire rst_n,
    output wire last,
    output wire pre_last,
    output reg [6:0] count // debug variable, 7 bits for values up to 127
);
  
  // Counter register with optimized width based on pMAX_VAL
  reg [6:0] int_count;
  
  // Initialize variables to avoid X values at simulation start
  initial begin
    int_count = pMAX_VAL;
    count = pMAX_VAL;
  end
  
  // Sequential logic for counter - optimized for clarity and efficiency
  always @(posedge clk or negedge rst_n) begin
    if(!rst_n) begin
      // Reset condition
      int_count <= pMAX_VAL;
      count <= pMAX_VAL;
    end
    else if(en) begin
      if(int_count > 0) begin
        // Normal counting
        int_count <= int_count - 1;
        count <= int_count - 1;
      end
      else begin
        // Wrap around when reached zero
        int_count <= pMAX_VAL;
        count <= pMAX_VAL;
      end
    end
    // Keep existing value when not enabled
  end
  
  // Optimized combinational logic for outputs - using assign for wire outputs
  assign last = (int_count == 0) ? 1'b1 : 1'b0;    // Explicit ternary to avoid X
  assign pre_last = (int_count == 1) ? 1'b1 : 1'b0; // Explicit ternary to avoid X
  
endmodule

Traffic_light_verilog/SecondCounter/Second_counter_tb.v
// Optimized testbench for Second_counter module - Fixed version
`timescale 1ns/1ps

module Second_counter_tb;
    // Define parameters
    parameter pSECOND_CNT_VALUE = 99;
    parameter pMAX_VAL = pSECOND_CNT_VALUE;
    parameter CLK_PERIOD = 4; // Clock period in ns
    
    // Testbench signals
    reg clk;  
    reg en;
    reg rst_n;
    wire last;
    wire pre_last;
    wire [6:0] count;
  
    // Instantiate the Unit Under Test (UUT)
    Second_counter #(
        .pSECOND_CNT_VALUE(pSECOND_CNT_VALUE),
        .pMAX_VAL(pMAX_VAL)
    ) uut (
        .clk(clk),
        .en(en),
        .rst_n(rst_n),
        .last(last),
        .pre_last(pre_last),
        .count(count)
    );
    
    // Initialize all signals to avoid X values
    initial begin
        clk = 0;
        en = 0;
        rst_n = 1;
    end
    
    // Clock generation
    always #(CLK_PERIOD/2) clk = ~clk;
    
    // Dump waveform to file
    initial begin
        $dumpfile("dump.vcd");
        $dumpvars(0, Second_counter_tb);
    end
  
    // Test sequence
    initial begin
        // Start with reset to ensure deterministic state
        #(CLK_PERIOD*2) rst_n = 0;
        #(CLK_PERIOD*2) rst_n = 1;
        
        // Enable counter and monitor - use %d for decimal display of count
        #(CLK_PERIOD) en = 1;
        $monitor("Time=%0t, clk=%b, rst_n=%b, en=%b, count=%d, last=%b, pre_last=%b", 
                 $time, clk, rst_n, en, count, last, pre_last);
        
        // Run for a full counter cycle plus a bit more to see wrap-around
        #(CLK_PERIOD * (pMAX_VAL + 10)) $finish;
    end
  
endmodule

SecondCounter/dump.vcd
$date
	Tue Jun 10 02:08:50 2025
$end
$version
	Icarus Verilog
$end
$timescale
	1ps
$end
$scope module Second_counter_tb $end
$var wire 1 ! pre_last $end
$var wire 1 " last $end
$var wire 7 # count [6:0] $end
$var parameter 32 $ CLK_PERIOD $end
$var parameter 32 % pMAX_VAL $end
$var parameter 32 & pSECOND_CNT_VALUE $end
$var reg 1 ' clk $end
$var reg 1 ( en $end
$var reg 1 ) rst_n $end
$scope module uut $end
$var wire 1 ' clk $end
$var wire 1 ( en $end
$var wire 1 ) rst_n $end
$var wire 1 ! pre_last $end
$var wire 1 " last $end
$var parameter 32 * pMAX_VAL $end
$var parameter 32 + pSECOND_CNT_VALUE $end
$var reg 7 , count [6:0] $end
$var reg 7 - int_count [6:0] $end
$upscope $end
$upscope $end
$enddefinitions $end
$comment Show the parameter values. $end
$dumpall
b1100011 +
b1100011 *
b1100011 &
b1100011 %
b100 $
$end
#0
$dumpvars
b1100011 -
b1100011 ,
1)
0(
0'
b1100011 #
0"
0!
$end
#2000
1'
#4000
0'
#6000
1'
#8000
0'
0)
#10000
1'
#12000
0'
#14000
1'
#16000
0'
1)
#18000
1'
#20000
0'
1(
#22000
b1100010 #
b1100010 ,
b1100010 -
1'
#24000
0'
#26000
b1100001 #
b1100001 ,
b1100001 -
1'
#28000
0'
#30000
b1100000 #
b1100000 ,
b1100000 -
1'
#32000
0'
#34000
b1011111 #
b1011111 ,
b1011111 -
1'
#36000
0'
#38000
b1011110 #
b1011110 ,
b1011110 -
1'
#40000
0'
#42000
b1011101 #
b1011101 ,
b1011101 -
1'
#44000
0'
#46000
b1011100 #
b1011100 ,
b1011100 -
1'
#48000
0'
#50000
b1011011 #
b1011011 ,
b1011011 -
1'
#52000
0'
#54000
b1011010 #
b1011010 ,
b1011010 -
1'
#56000
0'
#58000
b1011001 #
b1011001 ,
b1011001 -
1'
#60000
0'
#62000
b1011000 #
b1011000 ,
b1011000 -
1'
#64000
0'
#66000
b1010111 #
b1010111 ,
b1010111 -
1'
#68000
0'
#70000
b1010110 #
b1010110 ,
b1010110 -
1'
#72000
0'
#74000
b1010101 #
b1010101 ,
b1010101 -
1'
#76000
0'
#78000
b1010100 #
b1010100 ,
b1010100 -
1'
#80000
0'
#82000
b1010011 #
b1010011 ,
b1010011 -
1'
#84000
0'
#86000
b1010010 #
b1010010 ,
b1010010 -
1'
#88000
0'
#90000
b1010001 #
b1010001 ,
b1010001 -
1'
#92000
0'
#94000
b1010000 #
b1010000 ,
b1010000 -
1'
#96000
0'
#98000
b1001111 #
b1001111 ,
b1001111 -
1'
#100000
0'
#102000
b1001110 #
b1001110 ,
b1001110 -
1'
#104000
0'
#106000
b1001101 #
b1001101 ,
b1001101 -
1'
#108000
0'
#110000
b1001100 #
b1001100 ,
b1001100 -
1'
#112000
0'
#114000
b1001011 #
b1001011 ,
b1001011 -
1'
#116000
0'
#118000
b1001010 #
b1001010 ,
b1001010 -
1'
#120000
0'
#122000
b1001001 #
b1001001 ,
b1001001 -
1'
#124000
0'
#126000
b1001000 #
b1001000 ,
b1001000 -
1'
#128000
0'
#130000
b1000111 #
b1000111 ,
b1000111 -
1'
#132000
0'
#134000
b1000110 #
b1000110 ,
b1000110 -
1'
#136000
0'
#138000
b1000101 #
b1000101 ,
b1000101 -
1'
#140000
0'
#142000
b1000100 #
b1000100 ,
b1000100 -
1'
#144000
0'
#146000
b1000011 #
b1000011 ,
b1000011 -
1'
#148000
0'
#150000
b1000010 #
b1000010 ,
b1000010 -
1'
#152000
0'
#154000
b1000001 #
b1000001 ,
b1000001 -
1'
#156000
0'
#158000
b1000000 #
b1000000 ,
b1000000 -
1'
#160000
0'
#162000
b111111 #
b111111 ,
b111111 -
1'
#164000
0'
#166000
b111110 #
b111110 ,
b111110 -
1'
#168000
0'
#170000
b111101 #
b111101 ,
b111101 -
1'
#172000
0'
#174000
b111100 #
b111100 ,
b111100 -
1'
#176000
0'
#178000
b111011 #
b111011 ,
b111011 -
1'
#180000
0'
#182000
b111010 #
b111010 ,
b111010 -
1'
#184000
0'
#186000
b111001 #
b111001 ,
b111001 -
1'
#188000
0'
#190000
b111000 #
b111000 ,
b111000 -
1'
#192000
0'
#194000
b110111 #
b110111 ,
b110111 -
1'
#196000
0'
#198000
b110110 #
b110110 ,
b110110 -
1'
#200000
0'
#202000
b110101 #
b110101 ,
b110101 -
1'
#204000
0'
#206000
b110100 #
b110100 ,
b110100 -
1'
#208000
0'
#210000
b110011 #
b110011 ,
b110011 -
1'
#212000
0'
#214000
b110010 #
b110010 ,
b110010 -
1'
#216000
0'
#218000
b110001 #
b110001 ,
b110001 -
1'
#220000
0'
#222000
b110000 #
b110000 ,
b110000 -
1'
#224000
0'
#226000
b101111 #
b101111 ,
b101111 -
1'
#228000
0'
#230000
b101110 #
b101110 ,
b101110 -
1'
#232000
0'
#234000
b101101 #
b101101 ,
b101101 -
1'
#236000
0'
#238000
b101100 #
b101100 ,
b101100 -
1'
#240000
0'
#242000
b101011 #
b101011 ,
b101011 -
1'
#244000
0'
#246000
b101010 #
b101010 ,
b101010 -
1'
#248000
0'
#250000
b101001 #
b101001 ,
b101001 -
1'
#252000
0'
#254000
b101000 #
b101000 ,
b101000 -
1'
#256000
0'
#258000
b100111 #
b100111 ,
b100111 -
1'
#260000
0'
#262000
b100110 #
b100110 ,
b100110 -
1'
#264000
0'
#266000
b100101 #
b100101 ,
b100101 -
1'
#268000
0'
#270000
b100100 #
b100100 ,
b100100 -
1'
#272000
0'
#274000
b100011 #
b100011 ,
b100011 -
1'
#276000
0'
#278000
b100010 #
b100010 ,
b100010 -
1'
#280000
0'
#282000
b100001 #
b100001 ,
b100001 -
1'
#284000
0'
#286000
b100000 #
b100000 ,
b100000 -
1'
#288000
0'
#290000
b11111 #
b11111 ,
b11111 -
1'
#292000
0'
#294000
b11110 #
b11110 ,
b11110 -
1'
#296000
0'
#298000
b11101 #
b11101 ,
b11101 -
1'
#300000
0'
#302000
b11100 #
b11100 ,
b11100 -
1'
#304000
0'
#306000
b11011 #
b11011 ,
b11011 -
1'
#308000
0'
#310000
b11010 #
b11010 ,
b11010 -
1'
#312000
0'
#314000
b11001 #
b11001 ,
b11001 -
1'
#316000
0'
#318000
b11000 #
b11000 ,
b11000 -
1'
#320000
0'
#322000
b10111 #
b10111 ,
b10111 -
1'
#324000
0'
#326000
b10110 #
b10110 ,
b10110 -
1'
#328000
0'
#330000
b10101 #
b10101 ,
b10101 -
1'
#332000
0'
#334000
b10100 #
b10100 ,
b10100 -
1'
#336000
0'
#338000
b10011 #
b10011 ,
b10011 -
1'
#340000
0'
#342000
b10010 #
b10010 ,
b10010 -
1'
#344000
0'
#346000
b10001 #
b10001 ,
b10001 -
1'
#348000
0'
#350000
b10000 #
b10000 ,
b10000 -
1'
#352000
0'
#354000
b1111 #
b1111 ,
b1111 -
1'
#356000
0'
#358000
b1110 #
b1110 ,
b1110 -
1'
#360000
0'
#362000
b1101 #
b1101 ,
b1101 -
1'
#364000
0'
#366000
b1100 #
b1100 ,
b1100 -
1'
#368000
0'
#370000
b1011 #
b1011 ,
b1011 -
1'
#372000
0'
#374000
b1010 #
b1010 ,
b1010 -
1'
#376000
0'
#378000
b1001 #
b1001 ,
b1001 -
1'
#380000
0'
#382000
b1000 #
b1000 ,
b1000 -
1'
#384000
0'
#386000
b111 #
b111 ,
b111 -
1'
#388000
0'
#390000
b110 #
b110 ,
b110 -
1'
#392000
0'
#394000
b101 #
b101 ,
b101 -
1'
#396000
0'
#398000
b100 #
b100 ,
b100 -
1'
#400000
0'
#402000
b11 #
b11 ,
b11 -
1'
#404000
0'
#406000
b10 #
b10 ,
b10 -
1'
#408000
0'
#410000
1!
b1 #
b1 ,
b1 -
1'
#412000
0'
#414000
1"
0!
b0 #
b0 ,
b0 -
1'
#416000
0'
#418000
0"
b1100011 #
b1100011 ,
b1100011 -
1'
#420000
0'
#422000
b1100010 #
b1100010 ,
b1100010 -
1'
#424000
0'
#426000
b1100001 #
b1100001 ,
b1100001 -
1'
#428000
0'
#430000
b1100000 #
b1100000 ,
b1100000 -
1'
#432000
0'
#434000
b1011111 #
b1011111 ,
b1011111 -
1'
#436000
0'
#438000
b1011110 #
b1011110 ,
b1011110 -
1'
#440000
0'
#442000
b1011101 #
b1011101 ,
b1011101 -
1'
#444000
0'
#446000
b1011100 #
b1011100 ,
b1011100 -
1'
#448000
0'
#450000
b1011011 #
b1011011 ,
b1011011 -
1'
#452000
0'
#454000
b1011010 #
b1011010 ,
b1011010 -
1'
