TrafficLight/Light_FSM.v
// Light FSM module in Verilog
`timescale 1ns/1ps

module Light_FSM #(parameter LIGHT_STATE_WIDTH=3)(
  input wire clk,
  input wire en,
  input wire rst_n,
  input wire light_cnt_last,
  input wire second_cnt_pre_last,
  output wire [LIGHT_STATE_WIDTH-1:0] light,
  output wire [LIGHT_STATE_WIDTH-1:0] light_cnt_init
);
  // State definitions
  parameter IDLE = 2'b00;
  parameter GREEN = 2'b01;
  parameter YELLOW = 2'b10;
  parameter RED = 2'b11;
  
  // Light indices
  parameter pGREEN_IDX = 0;
  parameter pYELLOW_IDX = 1;
  parameter pRED_IDX = 2;
  
  // State registers
  reg [1:0] light_current_state, light_next_state;
  
  // Output signals
  reg [LIGHT_STATE_WIDTH-1:0] signal_current_light;
  reg [LIGHT_STATE_WIDTH-1:0] signal_current_init;
  reg [LIGHT_STATE_WIDTH-1:0] signal_next_light;
  reg [LIGHT_STATE_WIDTH-1:0] signal_next_init;
  
  // Last count signal
  wire last_cnt;
  
  // Assign outputs
  assign last_cnt = light_cnt_last & second_cnt_pre_last;
  assign light = signal_current_light;
  assign light_cnt_init = signal_current_init;
  
  // Sequential logic for state transitions
  always @(posedge clk or negedge rst_n) begin
    if(!rst_n) begin
      light_current_state <= IDLE;
      signal_current_light <= 0;
      signal_current_init <= 0;
    end
    else if(en) begin
      light_current_state <= light_next_state;
      signal_current_light <= signal_next_light;
      signal_current_init <= signal_next_init;
    end
    else begin
      light_current_state <= IDLE;
      signal_current_light <= 0;
      signal_current_init <= 0;
    end
  end
  
  // Combinational logic for next state and outputs
  always @(*) begin
    // Default values
    light_next_state = IDLE;
    signal_next_light = 0;
    signal_next_init = 0;
    
    case(light_current_state)
      IDLE: begin 
        if(en) begin
          light_next_state = GREEN;
          signal_next_light[pGREEN_IDX] = 1'b1;
          signal_next_init[pGREEN_IDX] = 1'b1;
        end
        else begin
          light_next_state = IDLE;
          signal_next_light = 0;
          signal_next_init = 0;
        end
      end
      
      GREEN: begin
        if(last_cnt) begin
          light_next_state = YELLOW;
          signal_next_light[pYELLOW_IDX] = 1'b1;
          signal_next_init[pYELLOW_IDX] = 1'b1;
        end
        else begin
          light_next_state = GREEN;
          signal_next_light[pGREEN_IDX] = 1'b1;
          signal_next_init[pGREEN_IDX] = 1'b1;
        end
      end
      
      YELLOW: begin 
        if(last_cnt) begin
          light_next_state = RED;
          signal_next_light[pRED_IDX] = 1'b1;
          signal_next_init[pRED_IDX] = 1'b1;
        end
        else begin
          light_next_state = YELLOW;
          signal_next_light[pYELLOW_IDX] = 1'b1;
          signal_next_init[pYELLOW_IDX] = 1'b1;
        end
      end
      
      RED: begin 
        if(last_cnt) begin
          light_next_state = GREEN;
          signal_next_light[pGREEN_IDX] = 1'b1;
          signal_next_init[pGREEN_IDX] = 1'b1;
        end
        else begin
          light_next_state = RED;
          signal_next_light[pRED_IDX] = 1'b1;
          signal_next_init[pRED_IDX] = 1'b1;
        end
      end
    endcase
  end
  
endmodule

Traffic_light_verilog/LightFSM/Light_FSM_tb.v
// Testbench for the Light_FSM module in Verilog
`timescale 1ns/1ps

module Light_FSM_tb;

  parameter LIGHT_STATE_WIDTH = 3;
  
  // Testbench signals
  reg clk;
  reg en;
  reg rst_n;
  reg light_cnt_last;
  reg second_cnt_pre_last;
  wire [LIGHT_STATE_WIDTH-1:0] light;
  wire [LIGHT_STATE_WIDTH-1:0] light_cnt_init;

  // Instantiate the Light_FSM module
  Light_FSM #(.LIGHT_STATE_WIDTH(LIGHT_STATE_WIDTH)) uut (
    .clk(clk),
    .en(en),
    .rst_n(rst_n),
    .light_cnt_last(light_cnt_last),
    .second_cnt_pre_last(second_cnt_pre_last),
    .light(light),
    .light_cnt_init(light_cnt_init)
  );

  // Clock generation
  always #5 clk = ~clk; // Toggle clock every 5 time units

  // Initial block for test setup
  initial begin
    $dumpfile("dump.vcd");
    $dumpvars(0, Light_FSM_tb);
    
    // Initialize signals
    clk = 0;
    en = 0;
    rst_n = 0;
    light_cnt_last = 0;
    second_cnt_pre_last = 0;
    
    // Apply reset
    #10;
    rst_n = 1;
    #10;
    rst_n = 0;
    #10;
    rst_n = 1;

    // Enable FSM
    en = 1;
    
    // Simulate light counter last signal
    #20; // Wait for some time
    light_cnt_last = 1;
    second_cnt_pre_last = 1; // Both counters indicate the last state
    #10;
    light_cnt_last = 0;
    second_cnt_pre_last = 0;
    
    #30;
    light_cnt_last = 1;
    second_cnt_pre_last = 1;
    #10;
    light_cnt_last = 0;
    second_cnt_pre_last = 0;
    
    #30;
    light_cnt_last = 1;
    second_cnt_pre_last = 1;
    #10;
    light_cnt_last = 0;
    second_cnt_pre_last = 0;

    #30;
    light_cnt_last = 1;
    second_cnt_pre_last = 1;
    #10;
    light_cnt_last = 0;
    second_cnt_pre_last = 0;

    // Complete simulation
    #100;
    $finish;
  end

  // Monitor states and outputs
  initial begin
    $monitor("Time=%t | State=%b | Light=%b | Init=%b",
             $time, uut.light_current_state, light, light_cnt_init);
  end
  
  // Task to display the current light state
  task display_light_state;
    begin
      if(light == 3'b100) begin
        $display("==========RED LIGHT==========");
      end
      else if(light == 3'b010) begin
        $display("==========YELLOW LIGHT==========");
      end
      else if(light == 3'b001) begin
        $display("==========GREEN LIGHT==========");
      end
      else begin
        $display("==========Count==========");
      end
    end
  endtask
  
  // Call display task on each positive clock edge
  always @(posedge clk) begin
     display_light_state;
  end
  
endmodule

Traffic_light_verilog/LightFSM/dump.vcd
$date
	Tue Jun 10 01:48:18 2025
$end
$version
	Icarus Verilog
$end
$timescale
	1ps
$end
$scope module Light_FSM_tb $end
$var wire 3 ! light_cnt_init [2:0] $end
$var wire 3 " light [2:0] $end
$var parameter 32 # LIGHT_STATE_WIDTH $end
$var reg 1 $ clk $end
$var reg 1 % en $end
$var reg 1 & light_cnt_last $end
$var reg 1 ' rst_n $end
$var reg 1 ( second_cnt_pre_last $end
$scope module uut $end
$var wire 1 $ clk $end
$var wire 1 % en $end
$var wire 1 ) last_cnt $end
$var wire 3 * light [2:0] $end
$var wire 3 + light_cnt_init [2:0] $end
$var wire 1 & light_cnt_last $end
$var wire 1 ' rst_n $end
$var wire 1 ( second_cnt_pre_last $end
$var parameter 2 , GREEN $end
$var parameter 2 - IDLE $end
$var parameter 32 . LIGHT_STATE_WIDTH $end
$var parameter 2 / RED $end
$var parameter 2 0 YELLOW $end
$var parameter 32 1 pGREEN_IDX $end
$var parameter 32 2 pRED_IDX $end
$var parameter 32 3 pYELLOW_IDX $end
$var reg 2 4 light_current_state [1:0] $end
$var reg 2 5 light_next_state [1:0] $end
$var reg 3 6 signal_current_init [2:0] $end
$var reg 3 7 signal_current_light [2:0] $end
$var reg 3 8 signal_next_init [2:0] $end
$var reg 3 9 signal_next_light [2:0] $end
$upscope $end
$scope task display_light_state $end
$upscope $end
$upscope $end
$enddefinitions $end
$comment Show the parameter values. $end
$dumpall
b1 3
b10 2
b0 1
b10 0
b11 /
b11 .
b0 -
b1 ,
b11 #
$end
#0
$dumpvars
b0 9
b0 8
b0 7
b0 6
b0 5
b0 4
b0 +
b0 *
0)
0(
0'
0&
0%
0$
b0 "
b0 !
$end
#5000
1$
#10000
0$
1'
#15000
1$
#20000
0$
0'
#25000
1$
#30000
b1 8
b1 9
b1 5
0$
1%
1'
#35000
b1 8
b1 9
b1 5
b1 !
b1 +
b1 6
b1 "
b1 *
b1 7
b1 4
1$
#40000
0$
#45000
1$
#50000
b10 8
b10 9
b10 5
1)
0$
1(
1&
#55000
b100 8
b100 9
b11 5
b10 !
b10 +
b10 6
b10 "
b10 *
b10 7
b10 4
1$
#60000
b10 8
b10 9
b10 5
0)
0$
0(
0&
#65000
1$
#70000
0$
#75000
1$
#80000
0$
#85000
1$
#90000
b100 8
b100 9
b11 5
1)
0$
1(
1&
#95000
b1 8
b1 9
b1 5
b100 !
b100 +
b100 6
b100 "
b100 *
b100 7
b11 4
1$
#100000
b100 8
b100 9
b11 5
0)
0$
0(
0&
#105000
1$
#110000
0$
#115000
1$
#120000
0$
#125000
1$
#130000
b1 8
b1 9
b1 5
1)
0$
1(
1&
#135000
b10 8
b10 9
b10 5
b1 !
b1 +
b1 6
b1 "
b1 *
b1 7
b1 4
1$
#140000
b1 8
b1 9
b1 5
0)
0$
0(
0&
#145000
1$
#150000
0$
#155000
1$
#160000
0$
#165000
1$
#170000
b10 8
b10 9
b10 5
1)
0$
1(
1&
#175000
b100 8
b100 9
b11 5
b10 !
b10 +
b10 6
b10 "
b10 *
b10 7
b10 4
1$
#180000
b10 8
b10 9
b10 5
0)
0$
0(
0&
